{"code": 0, "message": "0", "ttl": 1, "data": {"max_time": 4, "min_interval": 3600, "pull_interval": 3600, "list": [{"id": 4, "type": 2, "card_type": 14, "duration": 3, "begin_time": 1579449600, "end_time": 1582041599, "thumb": "https://i0.hdslb.com/bfs/sycp/tmaterial/201901/5b0f32e6b91e974ad7eb1ffca5328aec.jpg", "hash": "410cccec8e9b3025bde2d62c057d6685", "logo_url": "", "logo_hash": "", "skip": 0, "uri": "", "uri_title": "", "source": 929, "ad_cb": "<rm>", "resource_id": 926, "request_id": "<rm>", "client_ip": "47.92.120.142", "is_ad": false, "is_ad_loc": true, "extra": {"use_ad_web_v2": false, "show_urls": [], "click_urls": [], "download_whitelist": [], "report_time": 0, "sales_type": 41, "special_industry": false, "preload_landingpage": 0}}, {"id": 6, "type": 0, "card_type": 15, "duration": 3, "begin_time": 1514736000, "end_time": 2524579200, "thumb": "https://i0.hdslb.com/bfs/sycp/tmaterial/201805/122770e3b6e95389b5feb2830c0285de.png", "hash": "ec0078635307b6da8013daead6b14d85", "logo_url": "", "logo_hash": "", "skip": 0, "uri": "", "uri_title": "", "source": 929, "ad_cb": "<rm>", "resource_id": 926, "request_id": "<rm>", "client_ip": "47.92.120.142", "is_ad": false, "is_ad_loc": true, "extra": {"use_ad_web_v2": false, "show_urls": [], "click_urls": [], "download_whitelist": [], "report_time": 0, "sales_type": 41, "special_industry": false, "preload_landingpage": 0}}, {"id": 896, "type": 1, "card_type": 15, "duration": 3, "begin_time": 1560355200, "end_time": 1560441599, "thumb": "https://i0.hdslb.com/bfs/sycp/tmaterial/201905/c9d5e41f8dea72d12ed7f6604366e911.jpg", "hash": "3330ab5a93a324f506a205d8ccb9069f", "logo_url": "", "logo_hash": "", "skip": 1, "uri": "http://e.cn.miaozhen.com/r/k=2124360&p=7PNXg&dx=__IPDX__&rt=2&ns=__IP__&ni=__IESID__&v=__LOC__&xa=__ADPLATFORM__&tr=__REQUESTID__&mo=__OS__&m0=__OPENUDID__&m0a=__DUID__&m1=__ANDROIDID1__&m1a=__ANDROIDID__&m2=__IMEI__&m4=__AAID__&m5=__IDFA__&m6=__MAC1__&m6a=__MAC__&vo=3bca82b4e&vr=2&o=http%3A%2F%2Ftb.cn%2Fp2gfbEw", "uri_title": "\u6a58\u5b50\u6c7d\u6c34\uff0c\u70b9\u4eae\u590f\u65e5\uff0c\u5e72\u676f\uff01", "source": 929, "cm_mark": 1, "ad_cb": "<rm>", "resource_id": 926, "request_id": "<rm>", "client_ip": "47.92.120.142", "is_ad": true, "is_ad_loc": true, "schema_callup_white_list": ["tmall", "taobao", "ctrip", "openapp.jdmobile", "newsapp", "dianping", "vipshop", "kaola", "zhihu", "weixin", "alipays", "tbopen", "qunaraphone", "qunariphone"], "extra": {"use_ad_web_v2": true, "show_urls": [], "click_urls": [], "download_whitelist": [], "open_whitelist": ["tmall", "taobao", "ctrip", "openapp.jdmobile", "newsapp", "dianping", "vipshop", "kaola", "zhihu", "weixin", "alipays", "tbopen", "qunaraphone", "qunariphone"], "report_time": 0, "sales_type": 41, "special_industry": false, "preload_landingpage": 0}}, {"id": 928, "type": 1, "card_type": 15, "duration": 3, "begin_time": 1560268800, "end_time": 1560355199, "thumb": "https://i0.hdslb.com/bfs/sycp/tmaterial/201906/e25816782ed661a45daec9a6eb871abb.png", "hash": "de7c875c67a855fefefb44c47035661a", "logo_url": "", "logo_hash": "", "skip": 1, "uri": "http://ad.doubleclick.net/ddm/trackclk/N8897.2255701BILIBILI/B22799473.248744591;dc_trk_aid=445212359;dc_trk_cid=116972670", "uri_title": "\u6536\u773c\u888b \u5e73\u7ec6\u7eb9 \u517b\u776b\u6bdb", "source": 929, "cm_mark": 1, "ad_cb": "<rm>", "resource_id": 926, "request_id": "<rm>", "client_ip": "47.92.120.142", "is_ad": true, "is_ad_loc": true, "schema_callup_white_list": ["tmall", "taobao", "ctrip", "openapp.jdmobile", "newsapp", "dianping", "vipshop", "kaola", "zhihu", "weixin", "alipays", "tbopen", "qunaraphone", "qunariphone"], "extra": {"use_ad_web_v2": true, "show_urls": [], "click_urls": [], "download_whitelist": [], "open_whitelist": ["tmall", "taobao", "ctrip", "openapp.jdmobile", "newsapp", "dianping", "vipshop", "kaola", "zhihu", "weixin", "alipays", "tbopen", "qunaraphone", "qunariphone"], "report_time": 0, "sales_type": 41, "special_industry": false, "preload_landingpage": 0}}, {"id": 940, "type": 1, "card_type": 15, "duration": 3, "begin_time": 1560268800, "end_time": 1560355199, "thumb": "https://i0.hdslb.com/bfs/sycp/tmaterial/201906/0b2f91afe6e5d4df5a231c6dc02036dc.jpg", "hash": "3ce9fce11d9f5135fd7c428b7fb2deea", "logo_url": "", "logo_hash": "", "skip": 1, "uri": "https://ad.doubleclick.net/ddm/trackclk/N566410.3299537/B22830671.248682412;dc_trk_aid=444999799;dc_trk_cid=117312764;dc_lat=;dc_rdid=;tag_for_child_directed_treatment=;tfua=", "uri_title": "\u8054\u60f3340C\uff0c\u7acb\u5373\u62a2\u8d2d\uff01", "source": 929, "cm_mark": 1, "ad_cb": "<rm>", "resource_id": 926, "request_id": "<rm>", "client_ip": "47.92.120.142", "is_ad": true, "is_ad_loc": true, "schema_callup_white_list": ["tmall", "taobao", "ctrip", "openapp.jdmobile", "newsapp", "dianping", "vipshop", "kaola", "zhihu", "weixin", "alipays", "tbopen", "qunaraphone", "qunariphone"], "extra": {"use_ad_web_v2": true, "show_urls": [], "click_urls": [], "download_whitelist": [], "open_whitelist": ["tmall", "taobao", "ctrip", "openapp.jdmobile", "newsapp", "dianping", "vipshop", "kaola", "zhihu", "weixin", "alipays", "tbopen", "qunaraphone", "qunariphone"], "report_time": 0, "sales_type": 41, "special_industry": false, "preload_landingpage": 0}}, {"id": 943, "type": 1, "card_type": 16, "duration": 5, "begin_time": 1560528000, "end_time": 1560614399, "thumb": "https://i0.hdslb.com/bfs/sycp/ssa/default/201809/1a2414aaca0965d5a74974083e86a11f.png", "hash": "c9b22910c2120ccd67c52f08a1eac587", "logo_url": "", "logo_hash": "", "skip": 1, "uri": "http://e.cn.miaozhen.com/r/k=2124854&p=7PS8Y&dx=__IPDX__&rt=2&ns=__IP__&ni=__IESID__&v=__LOC__&xa=__ADPLATFORM__&tr=__REQUESTID__&mo=__OS__&m0=__OPENUDID__&m0a=__DUID__&m1=__ANDROIDID1__&m1a=__ANDROIDID__&m2=__IMEI__&m4=__AAID__&m5=__IDFA__&m6=__MAC1__&m6a=__MAC__&vo=334702a9f&vr=2&o=https%3A%2F%2Fmac.tmall.com%2F%3Fspm%3Da1z10.3-b-s.w14192001-16347915698.3.46f16db0ROJkGu", "video_url": "http://ssaxcode-upos-hz-cdn.acgvideo.com/m190611wsj45t1ucqcwrw3luaoivwure-1-SPLASH.mp4", "video_hash": "4e1128e200d2c39f84e86d68800d38ae", "video_width": 1080, "video_height": 1680, "uri_title": "\u5373\u523bGet\u5f20\u827a\u5174\u540c\u6b3e\u5e95\u5986", "source": 929, "cm_mark": 1, "ad_cb": "<rm>", "resource_id": 926, "request_id": "<rm>", "client_ip": "47.92.120.142", "is_ad": true, "is_ad_loc": true, "schema_callup_white_list": ["tmall", "taobao", "ctrip", "openapp.jdmobile", "newsapp", "dianping", "vipshop", "kaola", "zhihu", "weixin", "alipays", "tbopen", "qunaraphone", "qunariphone"], "extra": {"use_ad_web_v2": true, "show_urls": [], "click_urls": [], "download_whitelist": [], "open_whitelist": ["tmall", "taobao", "ctrip", "openapp.jdmobile", "newsapp", "dianping", "vipshop", "kaola", "zhihu", "weixin", "alipays", "tbopen", "qunaraphone", "qunariphone"], "report_time": 0, "sales_type": 41, "special_industry": false, "preload_landingpage": 0}}, {"id": 946, "type": 1, "card_type": 15, "duration": 3, "begin_time": 1560268800, "end_time": 1560355199, "thumb": "https://i0.hdslb.com/bfs/sycp/tmaterial/201906/ac36ec8a3f5d442f56d6df5edb9e4f8b.jpg", "hash": "131ad37c5d503a5afeb0aed10a73ef9f", "logo_url": "", "logo_hash": "", "skip": 1, "uri": "http://clickc.admaster.com.cn/c/a129486,b3503488,c3297,i0,m101,8a2,8b3,h", "uri_title": "\u4eac\u4e1c618\uff0c\u7535\u8111\u6570\u7801\u7206\u6b3e5\u6298\u62a2", "source": 929, "cm_mark": 1, "ad_cb": "<rm>", "resource_id": 926, "request_id": "<rm>", "client_ip": "47.92.120.142", "is_ad": true, "is_ad_loc": true, "schema_callup_white_list": ["tmall", "taobao", "ctrip", "openapp.jdmobile", "newsapp", "dianping", "vipshop", "kaola", "zhihu", "weixin", "alipays", "tbopen", "qunaraphone", "qunariphone"], "extra": {"use_ad_web_v2": true, "show_urls": [], "click_urls": [], "download_whitelist": [], "open_whitelist": ["tmall", "taobao", "ctrip", "openapp.jdmobile", "newsapp", "dianping", "vipshop", "kaola", "zhihu", "weixin", "alipays", "tbopen", "qunaraphone", "qunariphone"], "report_time": 0, "sales_type": 41, "special_industry": false, "preload_landingpage": 0}}, {"id": 949, "type": 1, "card_type": 15, "duration": 3, "begin_time": 1560355200, "end_time": 1560441599, "thumb": "https://i0.hdslb.com/bfs/sycp/tmaterial/201906/1554473a2e39b1d1fffb7cd8952571fa.jpg", "hash": "779c028f97af098e492821bce4546ee3", "logo_url": "", "logo_hash": "", "skip": 1, "uri": "http://clickc.admaster.com.cn/c/a128849,b3505692,c3297,i0,m101,8a2,8b3,h", "uri_title": "\u4eac\u4e1c618\uff0c\u90e8\u5206\u6ee1199\u51cf100", "source": 929, "cm_mark": 1, "ad_cb": "<rm>", "resource_id": 926, "request_id": "<rm>", "client_ip": "47.92.120.142", "is_ad": true, "is_ad_loc": true, "schema_callup_white_list": ["tmall", "taobao", "ctrip", "openapp.jdmobile", "newsapp", "dianping", "vipshop", "kaola", "zhihu", "weixin", "alipays", "tbopen", "qunaraphone", "qunariphone"], "extra": {"use_ad_web_v2": true, "show_urls": [], "click_urls": [], "download_whitelist": [], "open_whitelist": ["tmall", "taobao", "ctrip", "openapp.jdmobile", "newsapp", "dianping", "vipshop", "kaola", "zhihu", "weixin", "alipays", "tbopen", "qunaraphone", "qunariphone"], "report_time": 0, "sales_type": 41, "special_industry": false, "preload_landingpage": 0}}, {"id": 950, "type": 1, "card_type": 15, "duration": 3, "begin_time": 1560355200, "end_time": 1560441599, "thumb": "https://i0.hdslb.com/bfs/sycp/tmaterial/201906/0610770ddd611a72043c409c824de210.jpg", "hash": "71be627407a6cc1076cc846a834bc5de", "logo_url": "", "logo_hash": "", "skip": 1, "uri": "http://clickc.admaster.com.cn/c/a128701,b3506960,c3297,i0,m101,8a2,8b3,h", "uri_title": "\u4eac\u4e1c618\uff0c\u9650\u62a25\u6298\u795e\u5238", "source": 929, "cm_mark": 1, "ad_cb": "<rm>", "resource_id": 926, "request_id": "<rm>", "client_ip": "47.92.120.142", "is_ad": true, "is_ad_loc": true, "schema_callup_white_list": ["tmall", "taobao", "ctrip", "openapp.jdmobile", "newsapp", "dianping", "vipshop", "kaola", "zhihu", "weixin", "alipays", "tbopen", "qunaraphone", "qunariphone"], "extra": {"use_ad_web_v2": true, "show_urls": [], "click_urls": [], "download_whitelist": [], "open_whitelist": ["tmall", "taobao", "ctrip", "openapp.jdmobile", "newsapp", "dianping", "vipshop", "kaola", "zhihu", "weixin", "alipays", "tbopen", "qunaraphone", "qunariphone"], "report_time": 0, "sales_type": 41, "special_industry": false, "preload_landingpage": 0}}, {"id": 952, "type": 1, "card_type": 15, "duration": 3, "begin_time": 1560355200, "end_time": 1560441599, "thumb": "https://i0.hdslb.com/bfs/sycp/tmaterial/201906/56e52ff385066f244379c0883a574698.jpg", "hash": "0bedbb189201b13ff5affa7ebd3f9001", "logo_url": "", "logo_hash": "", "skip": 1, "uri": "https://www.bilibili.com/video/av55349972", "uri_title": "\u4eab\u53d7\u8db3\u7403\u5427\uff0c\u5973\u6218\u58eb\u4eec", "source": 929, "ad_cb": "<rm>", "resource_id": 926, "request_id": "<rm>", "client_ip": "47.92.120.142", "is_ad": true, "is_ad_loc": true, "extra": {"use_ad_web_v2": false, "show_urls": [], "click_urls": [], "download_whitelist": [], "open_whitelist": [], "report_time": 0, "sales_type": 41, "special_industry": false, "preload_landingpage": 0}}], "show": "<rm>"}}