{"code": 0, "message": "0", "ttl": 1, "data": {"max_time": 4, "min_interval": 14400, "pull_interval": 900, "list": [{"id": 4, "type": 2, "card_type": 14, "duration": 3, "begin_time": 1642608000, "end_time": 1645199999, "thumb": "https://i0.hdslb.com/bfs/sycp/creative_img/202101/d51ea7b0efee1f61ee50528aca512511.jpg", "hash": "00560265ff611d54cbdfcb0e142c3e34", "logo_url": "", "logo_hash": "", "skip": 0, "uri": "", "uri_title": "", "source": 929, "ad_cb": "<rm>", "resource_id": 926, "request_id": "<rm>", "client_ip": "47.92.120.142", "is_ad": false, "is_ad_loc": true, "schema_callup_white_list": ["dianping", "kaola", "vipshop", "ctrip", "bilibili", "mqq", "openapp.jdmobile", "taobao", "tbopen", "tmall", "weixin", "alipays", "sinaweibo", "pinduoduo", "SNKRS", "booking", "yohobuy", "alipay"], "extra": {"use_ad_web_v2": false, "show_urls": [], "click_urls": [], "download_whitelist": [], "open_whitelist": ["dianping", "kaola", "vipshop", "ctrip", "bilibili", "mqq", "openapp.jdmobile", "taobao", "tbopen", "tmall", "weixin", "alipays", "sinaweibo", "pinduoduo", "SNKRS", "booking", "yohobuy", "alipay"], "report_time": 0, "sales_type": 41, "special_industry": false, "preload_landingpage": 0, "share_info": {"image_url": ""}, "upzone_entrance_type": 0, "upzone_entrance_report_id": 0, "topview_pic_url": "", "topview_video_url": "", "click_area": 1, "shop_id": 0, "up_mid": 0, "track_id": "Th2hsAyNN5hahVeZIbUzZO03tn99Rf-1q9QxGf2Ysh-JTvdEKLUOOT1bPw770ggQZ6pQnf89si4A6PK7vwythllJ0HCjnHJCrZxqjZAEp04=", "enable_store_direct_launch": 0, "product_id": 0}, "enable_background_download": true}, {"id": 6, "type": 0, "card_type": 15, "duration": 3, "begin_time": 1514736000, "end_time": 2524579200, "thumb": "https://i0.hdslb.com/bfs/sycp/tmaterial/201805/122770e3b6e95389b5feb2830c0285de.png", "hash": "ec0078635307b6da8013daead6b14d85", "logo_url": "", "logo_hash": "", "skip": 0, "uri": "", "uri_title": "", "source": 929, "ad_cb": "<rm>", "resource_id": 926, "request_id": "<rm>", "client_ip": "47.92.120.142", "is_ad": false, "is_ad_loc": true, "schema_callup_white_list": ["dianping", "kaola", "vipshop", "ctrip", "bilibili", "mqq", "openapp.jdmobile", "taobao", "tbopen", "tmall", "weixin", "alipays", "sinaweibo", "pinduoduo", "SNKRS", "booking", "yohobuy", "alipay"], "extra": {"use_ad_web_v2": false, "show_urls": [], "click_urls": [], "download_whitelist": [], "open_whitelist": ["dianping", "kaola", "vipshop", "ctrip", "bilibili", "mqq", "openapp.jdmobile", "taobao", "tbopen", "tmall", "weixin", "alipays", "sinaweibo", "pinduoduo", "SNKRS", "booking", "yohobuy", "alipay"], "report_time": 0, "sales_type": 41, "special_industry": false, "preload_landingpage": 0, "share_info": {"image_url": ""}, "upzone_entrance_type": 0, "upzone_entrance_report_id": 0, "topview_pic_url": "", "topview_video_url": "", "click_area": 0, "shop_id": 0, "up_mid": 0, "track_id": "Th2hsAyNN5hahVeZIbUzZO03tn99Rf-1q9QxGf2Ysh_xLRhITXIL50-NZROqm6qqSz1r2pbkrBACcvtR-VDPKQjLBZ4mvJnWR5SFGXiwXZA=", "enable_store_direct_launch": 0, "product_id": 0}, "enable_background_download": true}, {"id": 4135, "type": 1, "card_type": 14, "duration": 3, "begin_time": 1621699200, "end_time": 1621785599, "thumb": "https://i0.hdslb.com/bfs/sycp/creative_img/202105/abca8b17a18d6f741bb51887872d69be.jpg", "hash": "edd0394a066d27ac0f4312317ed70974", "logo_url": "", "logo_hash": "", "skip": 1, "uri": "https://www.apple.com.cn/imac-24?cid=wwa-cn-dis-mac-clue-opa-nima-stil-:00s-916-cpd-prlp-bbli-mob-bro-na-na-mtt-q321-na-na-na-imac-green-nopri-buy-noctc-na-nobkg-na-na", "uri_title": "", "source": 929, "cm_mark": 1, "ad_cb": "<rm>", "resource_id": 926, "request_id": "<rm>", "client_ip": "47.92.120.142", "is_ad": true, "is_ad_loc": true, "schema_callup_white_list": ["tmall", "taobao", "openapp.jdmobile", "weixin", "alipays", "tbopen", "eleme", "qqmusic", "upwallet", "yocial://plaza/?tab=0", "hiapplink", "meiju", "midea-meiju", "uclink", "qklink", "taobaolite"], "extra": {"use_ad_web_v2": true, "show_urls": [], "click_urls": ["https://t.cr-nielsen.com/dar?_t=i&type=clk&v=1&_z=m&_inst=nl&hat_cid=315443&hat_pid=3887005&hat_aid=3325737&_crt=DISPLAY&_dt=PMP&_plt=MBL&os=__OS__&meid=__IMEI__&idfa=__IDFA__&oaid=__OAID__&mac=__MAC__&androidid=__ANDROIDID__&r=__TS__"], "download_whitelist": [], "open_whitelist": ["tmall", "taobao", "openapp.jdmobile", "weixin", "alipays", "tbopen", "eleme", "qqmusic", "upwallet", "yocial://plaza/?tab=0", "hiapplink", "meiju", "midea-meiju", "uclink", "qklink", "taobaolite"], "report_time": 0, "sales_type": 41, "special_industry": false, "preload_landingpage": 0, "share_info": {"image_url": ""}, "upzone_entrance_type": 0, "upzone_entrance_report_id": 0, "topview_pic_url": "", "topview_video_url": "", "click_area": 1, "shop_id": 0, "up_mid": 0, "track_id": "Th2hsAyNN5hahVeZIbUzZO03tn99Rf-1q9QxGf2Ysh-PMOKx-jzNsjtTIi6dfg-oJiFBPNTYp5fEXA-LnCkzE_zgunCKwunX0CBr-QHSat0=", "enable_store_direct_launch": 0, "product_id": 0}, "enable_pre_download": true, "enable_background_download": true}], "show": "<rm>"}}