{"code": 0, "message": "0", "ttl": 1, "data": {"max_time": 4, "min_interval": 14400, "pull_interval": 900, "list": [{"id": 4, "type": 2, "card_type": 14, "duration": 3, "begin_time": 1611072000, "end_time": 1613663999, "thumb": "https://i0.hdslb.com/bfs/sycp/creative_img/202001/fc95c2ffeab7b67f1dd857ce2e06f38f.jpg", "hash": "7f0e604e8f11b78ab87b08cd9374c842", "logo_url": "", "logo_hash": "", "skip": 0, "uri": "", "uri_title": "", "source": 929, "ad_cb": "<rm>", "resource_id": 926, "request_id": "<rm>", "client_ip": "47.92.120.142", "is_ad": false, "is_ad_loc": true, "schema_callup_white_list": ["dianping", "kaola", "vipshop", "ctrip", "bilibili", "mqq", "openapp.jdmobile", "taobao", "tbopen", "tmall", "weixin", "alipays", "sinaweibo", "pinduoduo", "SNKRS", "booking", "yohobuy", "eleme", "alipay"], "extra": {"use_ad_web_v2": false, "show_urls": [], "click_urls": [], "download_whitelist": [], "open_whitelist": ["dianping", "kaola", "vipshop", "ctrip", "bilibili", "mqq", "openapp.jdmobile", "taobao", "tbopen", "tmall", "weixin", "alipays", "sinaweibo", "pinduoduo", "SNKRS", "booking", "yohobuy", "eleme", "alipay"], "report_time": 0, "sales_type": 41, "special_industry": false, "preload_landingpage": 0, "share_info": {}, "upzone_entrance_type": 0, "upzone_entrance_report_id": 0, "topview_pic_url": "", "topview_video_url": "", "click_area": 0}, "enable_background_download": true}, {"id": 6, "type": 0, "card_type": 15, "duration": 3, "begin_time": 1514736000, "end_time": 2524579200, "thumb": "https://i0.hdslb.com/bfs/sycp/tmaterial/201805/122770e3b6e95389b5feb2830c0285de.png", "hash": "ec0078635307b6da8013daead6b14d85", "logo_url": "", "logo_hash": "", "skip": 0, "uri": "", "uri_title": "", "source": 929, "ad_cb": "<rm>", "resource_id": 926, "request_id": "<rm>", "client_ip": "47.92.120.142", "is_ad": false, "is_ad_loc": true, "schema_callup_white_list": ["dianping", "kaola", "vipshop", "ctrip", "bilibili", "mqq", "openapp.jdmobile", "taobao", "tbopen", "tmall", "weixin", "alipays", "sinaweibo", "pinduoduo", "SNKRS", "booking", "yohobuy", "eleme", "alipay"], "extra": {"use_ad_web_v2": false, "show_urls": [], "click_urls": [], "download_whitelist": [], "open_whitelist": ["dianping", "kaola", "vipshop", "ctrip", "bilibili", "mqq", "openapp.jdmobile", "taobao", "tbopen", "tmall", "weixin", "alipays", "sinaweibo", "pinduoduo", "SNKRS", "booking", "yohobuy", "eleme", "alipay"], "report_time": 0, "sales_type": 41, "special_industry": false, "preload_landingpage": 0, "share_info": {}, "upzone_entrance_type": 0, "upzone_entrance_report_id": 0, "topview_pic_url": "", "topview_video_url": "", "click_area": 0}, "enable_background_download": true}, {"id": 2164, "type": 1, "card_type": 14, "duration": 3, "begin_time": 1592236800, "end_time": 1592323199, "thumb": "https://i0.hdslb.com/bfs/sycp/creative_img/202006/7440317bb6f11cb6c327545ad21fd810.jpg", "hash": "bda8507dbe454acb0ddbf80608f97e40", "logo_url": "", "logo_hash": "", "skip": 1, "uri": "https://click.tanx.com/tfn?e=P1%2fzPoeZw5qfyurHMk0ftcOZP7pRXVmWd2VikvfCygNETeaY8mdtlG0Bv7NeoFByBufPa%2b8o8tIEiRMcGA363kCS7AMSPK8y3FbO9Vcuq3doh6t2Ou79MkAg%2bWElSh0WKJgzS%2bNWQ70%3d&u=https%3a%2f%2fmarket.m.taobao.com%2fapp%2ftb-source-app%2fshopact%2fpages%2findex%3f%26pathInfo%3dshop%2factivity%26userId%3d3527212490%26shopId%3d434208197%26pageId%3d225825682%26alisite%3dtrue%26bc_fl_src%3dtanx_df_147382634_0_17432_186029_58474_11633_10462_3%26resource_id%3d17432&k=140&ext=a%3d__IMEI__%26b%3d__IDFA__%26c%3d__MAC__%26d%3d__OAID__", "uri_title": "", "source": 929, "cm_mark": 1, "ad_cb": "<rm>", "resource_id": 926, "request_id": "<rm>", "client_ip": "47.92.120.142", "is_ad": true, "is_ad_loc": true, "schema": "tbopen://m.taobao.com/tbopen/index.html?action=ali.open.nav&bootImage=0&module=h5&source=alimama&visa=5d429034ad046701&appkey=24815762&bc_fl_src=tanx_df_147382634_0_17432_186029_58474_11633_10462_3&backURL=bilibili%3A%2F%2Fblank%3Fcm_mark%3Dxxx&packageName=AdxConstants.ANDROID_APP_PACKAGE_NAME&h5Url=https%3A%2F%2Fclick.tanx.com%2Ftfn%3Fe%3DP1%252fzPoeZw5qfyurHMk0ftcOZP7pRXVmWd2VikvfCygNETeaY8mdtlG0Bv7NeoFByBufPa%252b8o8tIEiRMcGA363kCS7AMSPK8y3FbO9Vcuq3doh6t2Ou79MkAg%252bWElSh0WKJgzS%252bNWQ70%253d%26u%3Dhttps%253a%252f%252fmarket.m.taobao.com%252fapp%252ftb-source-app%252fshopact%252fpages%252findex%253f%2526pathInfo%253dshop%252factivity%2526userId%253d3527212490%2526shopId%253d434208197%2526pageId%253d225825682%2526alisite%253dtrue%2526bc_fl_src%253dtanx_df_147382634_0_17432_186029_58474_11633_10462_3%2526resource_id%253d17432%26k%3D140%26ext%3Da%253d__IMEI__%2526b%253d__IDFA__%2526c%253d__MAC__%2526d%253d__OAID__", "schema_title": "\u7acb\u5373\u67e5\u770b", "schema_package_name": "com.taobao.taobao", "schema_callup_white_list": ["tmall", "taobao", "ctrip", "openapp.jdmobile", "newsapp", "dianping", "vipshop", "kaola", "weixin", "alipays", "tbopen", "qunaraphone", "qunariphone", "eleme", "airbnb", "pddopen"], "universal_app": "tbopen://m.taobao.com/tbopen/index.html?action=ali.open.nav&bootImage=0&module=h5&source=alimama&visa=5d429034ad046701&appkey=24815762&bc_fl_src=tanx_df_147382634_0_17432_186029_58474_11633_10462_3&backURL=bilibili%3A%2F%2Fblank%3Fcm_mark%3Dxxx&packageName=AdxConstants.ANDROID_APP_PACKAGE_NAME&h5Url=https%3A%2F%2Fclick.tanx.com%2Ftfn%3Fe%3DP1%252fzPoeZw5qfyurHMk0ftcOZP7pRXVmWd2VikvfCygNETeaY8mdtlG0Bv7NeoFByBufPa%252b8o8tIEiRMcGA363kCS7AMSPK8y3FbO9Vcuq3doh6t2Ou79MkAg%252bWElSh0WKJgzS%252bNWQ70%253d%26u%3Dhttps%253a%252f%252fmarket.m.taobao.com%252fapp%252ftb-source-app%252fshopact%252fpages%252findex%253f%2526pathInfo%253dshop%252factivity%2526userId%253d3527212490%2526shopId%253d434208197%2526pageId%253d225825682%2526alisite%253dtrue%2526bc_fl_src%253dtanx_df_147382634_0_17432_186029_58474_11633_10462_3%2526resource_id%253d17432%26k%3D140%26ext%3Da%253d__IMEI__%2526b%253d__IDFA__%2526c%253d__MAC__%2526d%253d__OAID__", "extra": {"use_ad_web_v2": true, "show_urls": ["https://g.cn.miaozhen.com/x/k=2170608&p=7aKyA&dx=__IPDX__&rt=2&pro=s&ns=__IP__&ni=__IESID__&v=__LOC__&xa=__ADPLATFORM__&tr=__REQUESTID__&vg=__AUTOPLAY__&nh=__AUTOREFRESH__&ai=__AIID__&o=https://ef-dongfeng.tanx.com/nnim?e=YsJ7Jzds2iSgsWqVnuydz6Nwj84Yxx0NIq2lIhroRNxNI3KpE0TLIBqe_UFBokeR6kUaUuxum1E-fWGqK2eccOOtOnnqSEbsVbtBZ4dR4gUnYhYjAcm_dsR3LApf81IA&k=129&a1=__IP__&a2=__OS__&a3=__IDFA__&a4=__IMEI__&a5=__IMEI_MD5__&a6=__OAID__&a7=__MAC__&a8=__UA__&a9=__TS__"], "click_urls": ["https://e.cn.miaozhen.com/r/k=2170608&p=7aKyA&dx=__IPDX__&rt=2&pro=s&ns=__IP__&ni=__IESID__&v=__LOC__&xa=__ADPLATFORM__&tr=__REQUESTID__&ai=__AIID__&o=https://ef-dongfeng.tanx.com/nncm?e=YsJ7Jzds2iSgsWqVnuydz6Nwj84Yxx0NIq2lIhroRNxNI3KpE0TLIBqe_UFBokeR6kUaUuxum1E-fWGqK2eccOOtOnnqSEbsVbtBZ4dR4gUnYhYjAcm_dsR3LApf81IA&k=129&a1=__IP__&a2=__OS__&a3=__IDFA__&a4=__IMEI__&a5=__IMEI_MD5__&a6=__OAID__&a7=__MAC__&a8=__UA__&a9=__TS__"], "download_whitelist": [], "open_whitelist": ["tmall", "taobao", "ctrip", "openapp.jdmobile", "newsapp", "dianping", "vipshop", "kaola", "weixin", "alipays", "tbopen", "qunaraphone", "qunariphone", "eleme", "airbnb", "pddopen"], "report_time": 0, "sales_type": 41, "special_industry": false, "preload_landingpage": 0, "share_info": {}, "upzone_entrance_type": 0, "upzone_entrance_report_id": 0, "topview_pic_url": "", "topview_video_url": "", "click_area": 1}, "enable_pre_download": true, "enable_background_download": true}, {"id": 2230, "type": 1, "card_type": 15, "duration": 3, "begin_time": 1592150400, "end_time": 1592236799, "thumb": "https://i0.hdslb.com/bfs/sycp/creative_img/202006/260284eebfcd1f2c9b2baef16d14751f.jpg", "hash": "cdd3d3f50861edc39ddb9f79ec7c1d0e", "logo_url": "", "logo_hash": "", "skip": 1, "uri": "https://equity.tmall.com/tm?agentId=603005&_bind=true&bc_fl_src=tmall_market_llb_1_767629&llbPlatform=_pube&llbOsd=1", "uri_title": "\u8f7b\u8584\u9632\u6652\u4e0d\u95f7\u75d8", "source": 929, "cm_mark": 1, "ad_cb": "<rm>", "resource_id": 926, "request_id": "<rm>", "client_ip": "47.92.120.142", "is_ad": true, "is_ad_loc": true, "schema": "tbopen://m.taobao.com/tbopen/index.html?action=ali.open.nav&module=h5&bootImage=0&source=alimama&appkey=27696150&appName=bilibili&packageName=tv.danmaku.bili&backURL=bilibili%3A%2F%2Fblank%3Fcm_mark%3Dtaobao&h5Url=https%3a%2f%2fequity.tmall.com%2ftm%3fagentId%3d603005%26_bind%3dtrue%26bc_fl_src%3dtmall_market_llb_1_767629%26llbPlatform%3d_pube%26llbOsd%3d1", "schema_title": "\u7acb\u5373\u67e5\u770b", "schema_package_name": "com.taobao.taobao", "schema_callup_white_list": ["tmall", "taobao", "ctrip", "openapp.jdmobile", "newsapp", "dianping", "vipshop", "kaola", "weixin", "alipays", "tbopen", "qunaraphone", "qunariphone", "eleme", "airbnb", "pddopen"], "universal_app": "tbopen://m.taobao.com/tbopen/index.html?action=ali.open.nav&module=h5&bootImage=0&source=alimama&appkey=27696150&appName=bilibili&packageName=tv.danmaku.bili&backURL=bilibili%3A%2F%2Fblank%3Fcm_mark%3Dtaobao&h5Url=https%3a%2f%2fequity.tmall.com%2ftm%3fagentId%3d603005%26_bind%3dtrue%26bc_fl_src%3dtmall_market_llb_1_767629%26llbPlatform%3d_pube%26llbOsd%3d1", "extra": {"use_ad_web_v2": true, "show_urls": [], "click_urls": ["https://e.cn.miaozhen.com/r/k=2169132&p=7a8Ew&dx=__IPDX__&rt=2&pro=s&ns=__IP__&ni=__IESID__&v=__LOC__&xa=__ADPLATFORM__&tr=__REQUESTID__&mo=__OS__&m0=__OPENUDID__&m0a=__DUID__&m1=__ANDROIDID1__&m1a=__ANDROIDID__&m2=__IMEI__&m4=__AAID__&m5=__IDFA__&m6=__MAC1__&m6a=__MAC__&m11=__OAID__&mn=__ANAME__&o=http://trace.rtbasia.com/tkp?rta_k=V2TLBELA00&utm_source=Bilibili&utm_medium=DISP&utm_content=Opening&utm_campaign=CN_20200615_UV_Bilibili_CPD_LRL_FS_Regular_NVD_DISP_MO&device=MO&imei=__IMEI__&mac=__MAC__&idfa=__IDFA__&androidid=__ANDROIDID__&oaid=__OAID__&forward="], "download_whitelist": [], "open_whitelist": ["tmall", "taobao", "ctrip", "openapp.jdmobile", "newsapp", "dianping", "vipshop", "kaola", "weixin", "alipays", "tbopen", "qunaraphone", "qunariphone", "eleme", "airbnb", "pddopen"], "report_time": 0, "sales_type": 41, "special_industry": false, "preload_landingpage": 0, "share_info": {}, "upzone_entrance_type": 0, "upzone_entrance_report_id": 0, "topview_pic_url": "", "topview_video_url": "", "click_area": 0}, "enable_pre_download": true, "enable_background_download": true}, {"id": 2240, "type": 1, "card_type": 14, "duration": 3, "begin_time": 1592150400, "end_time": 1592236799, "thumb": "https://i0.hdslb.com/bfs/sycp/creative_img/202006/aa0e93ed86652401a36c4a3a5f2b2e5f.jpg", "hash": "a1cca269556f854e0f4583e673fbe13b", "logo_url": "", "logo_hash": "", "skip": 1, "uri": "https://click.tanx.com/tfn?e=nSbqjYJMSwSpkqsHTUBO9yVzUgGGyYmmd2VikvfCygNETeaY8mdtlG0Bv7NeoFByBufPa%2b8o8tI7MPkz6vwMIpsS%2b8glEvWPhOViAsnHL07CJ%2fRR2dzkz0Ag%2bWElSh0WKJgzS%2bNWQ70%3d&u=https%3a%2f%2f618.tmall.com%2fmedia%3fdisableNav%3dYES%26bc_fl_src%3dtanx_df_147382634_0_17432_190808_59429_11872_10691_3%26resource_id%3d17432&k=140&ext=a%3d__IMEI__%26b%3d__IDFA__%26c%3d__MAC__%26d%3d__OAID__", "uri_title": "", "source": 929, "cm_mark": 1, "ad_cb": "<rm>", "resource_id": 926, "request_id": "<rm>", "client_ip": "47.92.120.142", "is_ad": true, "is_ad_loc": true, "schema": "tbopen://m.taobao.com/tbopen/index.html?action=ali.open.nav&bootImage=0&module=h5&source=alimama&visa=5d429034ad046701&appkey=24815762&bc_fl_src=tanx_df_147382634_0_17432_190808_59429_11872_10691_3&backURL=bilibili%3A%2F%2Fblank%3Fcm_mark%3Dxxx&packageName=AdxConstants.ANDROID_APP_PACKAGE_NAME&h5Url=https%3A%2F%2Fclick.tanx.com%2Ftfn%3Fe%3D3WxOfyxf%252f%252boN2WBaMN8K0QJR9P%252fmCwQWd2VikvfCygNETeaY8mdtlG0Bv7NeoFByBufPa%252b8o8tI7MPkz6vwMIpsS%252b8glEvWPhOViAsnHL07CJ%252fRR2dzkz0Ag%252bWElSh0WKJgzS%252bNWQ70%253d%26u%3Dhttps%253a%252f%252f618.tmall.com%252fmedia%253fdisableNav%253dYES%2526resource_id%253d17432%26k%3D140%26ext%3Da%253d__IMEI__%2526b%253d__IDFA__%2526c%253d__MAC__%2526d%253d__OAID__", "schema_title": "\u7acb\u5373\u67e5\u770b", "schema_package_name": "com.taobao.taobao", "schema_callup_white_list": ["tmall", "taobao", "ctrip", "openapp.jdmobile", "newsapp", "dianping", "vipshop", "kaola", "weixin", "alipays", "tbopen", "qunaraphone", "qunariphone", "eleme", "airbnb", "pddopen"], "universal_app": "tbopen://m.taobao.com/tbopen/index.html?action=ali.open.nav&bootImage=0&module=h5&source=alimama&visa=5d429034ad046701&appkey=24815762&bc_fl_src=tanx_df_147382634_0_17432_190808_59429_11872_10691_3&backURL=bilibili%3A%2F%2Fblank%3Fcm_mark%3Dxxx&packageName=AdxConstants.ANDROID_APP_PACKAGE_NAME&h5Url=https%3A%2F%2Fclick.tanx.com%2Ftfn%3Fe%3D3WxOfyxf%252f%252boN2WBaMN8K0QJR9P%252fmCwQWd2VikvfCygNETeaY8mdtlG0Bv7NeoFByBufPa%252b8o8tI7MPkz6vwMIpsS%252b8glEvWPhOViAsnHL07CJ%252fRR2dzkz0Ag%252bWElSh0WKJgzS%252bNWQ70%253d%26u%3Dhttps%253a%252f%252f618.tmall.com%252fmedia%253fdisableNav%253dYES%2526resource_id%253d17432%26k%3D140%26ext%3Da%253d__IMEI__%2526b%253d__IDFA__%2526c%253d__MAC__%2526d%253d__OAID__", "extra": {"use_ad_web_v2": true, "show_urls": ["https://ef-dongfeng.tanx.com/nnim?e=GmZjIC992oOgsWqVnuydz6Nwj84Yxx0NIq2lIhroRNxNI3KpE0TLIBqe_UFBokeRUAscoD_eyvAIkwt_bS0HduOtOnnqSEbs507zdlVLKIq5DIxv5EGl0uBq--JhPSpE&k=129&a1=__IP__&a2=__OS__&a3=__IDFA__&a4=__IMEI__&a5=__IMEI_MD5__&a6=__OAID__&a7=__MAC__&a8=__UA__&a9=__TS__"], "click_urls": ["https://ef-dongfeng.tanx.com/nncm?e=GmZjIC992oOgsWqVnuydz6Nwj84Yxx0NIq2lIhroRNxNI3KpE0TLIBqe_UFBokeRUAscoD_eyvAIkwt_bS0HduOtOnnqSEbs507zdlVLKIq5DIxv5EGl0uBq--JhPSpE&k=129&a1=__IP__&a2=__OS__&a3=__IDFA__&a4=__IMEI__&a5=__IMEI_MD5__&a6=__OAID__&a7=__MAC__&a8=__UA__&a9=__TS__"], "download_whitelist": [], "open_whitelist": ["tmall", "taobao", "ctrip", "openapp.jdmobile", "newsapp", "dianping", "vipshop", "kaola", "weixin", "alipays", "tbopen", "qunaraphone", "qunariphone", "eleme", "airbnb", "pddopen"], "report_time": 0, "sales_type": 41, "special_industry": false, "preload_landingpage": 0, "share_info": {}, "upzone_entrance_type": 0, "upzone_entrance_report_id": 0, "topview_pic_url": "", "topview_video_url": "", "click_area": 1}, "enable_pre_download": true, "enable_background_download": true}, {"id": 2241, "type": 1, "card_type": 14, "duration": 3, "begin_time": 1592150400, "end_time": 1592236799, "thumb": "https://i0.hdslb.com/bfs/sycp/creative_img/202006/a6087fcf62f44fc7e7559850f50ffb54.jpg", "hash": "a2059f32817a4db641f94607529c12a8", "logo_url": "", "logo_hash": "", "skip": 1, "uri": "https://click.tanx.com/tfn?e=nSbqjYJMSwSpkqsHTUBO9yVzUgGGyYmmd2VikvfCygNETeaY8mdtlG0Bv7NeoFByBufPa%2b8o8tI7MPkz6vwMIpsS%2b8glEvWPhOViAsnHL07CJ%2fRR2dzkz0Ag%2bWElSh0WKJgzS%2bNWQ70%3d&u=https%3a%2f%2f618.tmall.com%2fmedia%3fdisableNav%3dYES%26bc_fl_src%3dtanx_df_147382634_0_17432_190808_59429_11872_10691_3%26resource_id%3d17432&k=140&ext=a%3d__IMEI__%26b%3d__IDFA__%26c%3d__MAC__%26d%3d__OAID__", "uri_title": "", "source": 929, "cm_mark": 1, "ad_cb": "<rm>", "resource_id": 926, "request_id": "<rm>", "client_ip": "47.92.120.142", "is_ad": true, "is_ad_loc": true, "schema": "tbopen://m.taobao.com/tbopen/index.html?action=ali.open.nav&bootImage=0&module=h5&source=alimama&visa=5d429034ad046701&appkey=24815762&bc_fl_src=tanx_df_147382634_0_17432_190808_59429_11872_10691_3&backURL=bilibili%3A%2F%2Fblank%3Fcm_mark%3Dxxx&packageName=AdxConstants.ANDROID_APP_PACKAGE_NAME&h5Url=https%3A%2F%2Fclick.tanx.com%2Ftfn%3Fe%3D3WxOfyxf%252f%252boN2WBaMN8K0QJR9P%252fmCwQWd2VikvfCygNETeaY8mdtlG0Bv7NeoFByBufPa%252b8o8tI7MPkz6vwMIpsS%252b8glEvWPhOViAsnHL07CJ%252fRR2dzkz0Ag%252bWElSh0WKJgzS%252bNWQ70%253d%26u%3Dhttps%253a%252f%252f618.tmall.com%252fmedia%253fdisableNav%253dYES%2526resource_id%253d17432%26k%3D140%26ext%3Da%253d__IMEI__%2526b%253d__IDFA__%2526c%253d__MAC__%2526d%253d__OAID__", "schema_title": "\u7acb\u5373\u67e5\u770b", "schema_package_name": "com.taobao.taobao", "schema_callup_white_list": ["tmall", "taobao", "ctrip", "openapp.jdmobile", "newsapp", "dianping", "vipshop", "kaola", "weixin", "alipays", "tbopen", "qunaraphone", "qunariphone", "eleme", "airbnb", "pddopen"], "universal_app": "tbopen://m.taobao.com/tbopen/index.html?action=ali.open.nav&bootImage=0&module=h5&source=alimama&visa=5d429034ad046701&appkey=24815762&bc_fl_src=tanx_df_147382634_0_17432_190808_59429_11872_10691_3&backURL=bilibili%3A%2F%2Fblank%3Fcm_mark%3Dxxx&packageName=AdxConstants.ANDROID_APP_PACKAGE_NAME&h5Url=https%3A%2F%2Fclick.tanx.com%2Ftfn%3Fe%3D3WxOfyxf%252f%252boN2WBaMN8K0QJR9P%252fmCwQWd2VikvfCygNETeaY8mdtlG0Bv7NeoFByBufPa%252b8o8tI7MPkz6vwMIpsS%252b8glEvWPhOViAsnHL07CJ%252fRR2dzkz0Ag%252bWElSh0WKJgzS%252bNWQ70%253d%26u%3Dhttps%253a%252f%252f618.tmall.com%252fmedia%253fdisableNav%253dYES%2526resource_id%253d17432%26k%3D140%26ext%3Da%253d__IMEI__%2526b%253d__IDFA__%2526c%253d__MAC__%2526d%253d__OAID__", "extra": {"use_ad_web_v2": true, "show_urls": ["https://ef-dongfeng.tanx.com/nnim?e=GmZjIC992oOgsWqVnuydz6Nwj84Yxx0NIq2lIhroRNxNI3KpE0TLIBqe_UFBokeRUAscoD_eyvAIkwt_bS0HduOtOnnqSEbs507zdlVLKIq5DIxv5EGl0uBq--JhPSpE&k=129&a1=__IP__&a2=__OS__&a3=__IDFA__&a4=__IMEI__&a5=__IMEI_MD5__&a6=__OAID__&a7=__MAC__&a8=__UA__&a9=__TS__"], "click_urls": ["https://ef-dongfeng.tanx.com/nncm?e=GmZjIC992oOgsWqVnuydz6Nwj84Yxx0NIq2lIhroRNxNI3KpE0TLIBqe_UFBokeRUAscoD_eyvAIkwt_bS0HduOtOnnqSEbs507zdlVLKIq5DIxv5EGl0uBq--JhPSpE&k=129&a1=__IP__&a2=__OS__&a3=__IDFA__&a4=__IMEI__&a5=__IMEI_MD5__&a6=__OAID__&a7=__MAC__&a8=__UA__&a9=__TS__"], "download_whitelist": [], "open_whitelist": ["tmall", "taobao", "ctrip", "openapp.jdmobile", "newsapp", "dianping", "vipshop", "kaola", "weixin", "alipays", "tbopen", "qunaraphone", "qunariphone", "eleme", "airbnb", "pddopen"], "report_time": 0, "sales_type": 41, "special_industry": false, "preload_landingpage": 0, "share_info": {}, "upzone_entrance_type": 0, "upzone_entrance_report_id": 0, "topview_pic_url": "", "topview_video_url": "", "click_area": 1}, "enable_pre_download": true, "enable_background_download": true}, {"id": 2242, "type": 1, "card_type": 14, "duration": 3, "begin_time": 1592236800, "end_time": 1592323199, "thumb": "https://i0.hdslb.com/bfs/sycp/creative_img/202006/e37a619ba62c87f87f2d9b3e3642ca50.jpg", "hash": "d73cc9720c7e2feeabe95be9857aea73", "logo_url": "", "logo_hash": "", "skip": 1, "uri": "https://click.tanx.com/tfn?e=nSbqjYJMSwSpkqsHTUBO9yVzUgGGyYmmd2VikvfCygNETeaY8mdtlG0Bv7NeoFByBufPa%2b8o8tI7MPkz6vwMIpsS%2b8glEvWPhOViAsnHL07CJ%2fRR2dzkz0Ag%2bWElSh0WKJgzS%2bNWQ70%3d&u=https%3a%2f%2f618.tmall.com%2fmedia%3fdisableNav%3dYES%26bc_fl_src%3dtanx_df_147382634_0_17432_190808_59429_11872_10691_3%26resource_id%3d17432&k=140&ext=a%3d__IMEI__%26b%3d__IDFA__%26c%3d__MAC__%26d%3d__OAID__", "uri_title": "", "source": 929, "cm_mark": 1, "ad_cb": "<rm>", "resource_id": 926, "request_id": "<rm>", "client_ip": "47.92.120.142", "is_ad": true, "is_ad_loc": true, "schema": "tbopen://m.taobao.com/tbopen/index.html?action=ali.open.nav&bootImage=0&module=h5&source=alimama&visa=5d429034ad046701&appkey=24815762&bc_fl_src=tanx_df_147382634_0_17432_190808_59429_11872_10691_3&backURL=bilibili%3A%2F%2Fblank%3Fcm_mark%3Dxxx&packageName=AdxConstants.ANDROID_APP_PACKAGE_NAME&h5Url=https%3A%2F%2Fclick.tanx.com%2Ftfn%3Fe%3D3WxOfyxf%252f%252boN2WBaMN8K0QJR9P%252fmCwQWd2VikvfCygNETeaY8mdtlG0Bv7NeoFByBufPa%252b8o8tI7MPkz6vwMIpsS%252b8glEvWPhOViAsnHL07CJ%252fRR2dzkz0Ag%252bWElSh0WKJgzS%252bNWQ70%253d%26u%3Dhttps%253a%252f%252f618.tmall.com%252fmedia%253fdisableNav%253dYES%2526resource_id%253d17432%26k%3D140%26ext%3Da%253d__IMEI__%2526b%253d__IDFA__%2526c%253d__MAC__%2526d%253d__OAID__", "schema_title": "\u7acb\u5373\u67e5\u770b", "schema_package_name": "com.taobao.taobao", "schema_callup_white_list": ["tmall", "taobao", "ctrip", "openapp.jdmobile", "newsapp", "dianping", "vipshop", "kaola", "weixin", "alipays", "tbopen", "qunaraphone", "qunariphone", "eleme", "airbnb", "pddopen"], "universal_app": "tbopen://m.taobao.com/tbopen/index.html?action=ali.open.nav&bootImage=0&module=h5&source=alimama&visa=5d429034ad046701&appkey=24815762&bc_fl_src=tanx_df_147382634_0_17432_190808_59429_11872_10691_3&backURL=bilibili%3A%2F%2Fblank%3Fcm_mark%3Dxxx&packageName=AdxConstants.ANDROID_APP_PACKAGE_NAME&h5Url=https%3A%2F%2Fclick.tanx.com%2Ftfn%3Fe%3D3WxOfyxf%252f%252boN2WBaMN8K0QJR9P%252fmCwQWd2VikvfCygNETeaY8mdtlG0Bv7NeoFByBufPa%252b8o8tI7MPkz6vwMIpsS%252b8glEvWPhOViAsnHL07CJ%252fRR2dzkz0Ag%252bWElSh0WKJgzS%252bNWQ70%253d%26u%3Dhttps%253a%252f%252f618.tmall.com%252fmedia%253fdisableNav%253dYES%2526resource_id%253d17432%26k%3D140%26ext%3Da%253d__IMEI__%2526b%253d__IDFA__%2526c%253d__MAC__%2526d%253d__OAID__", "extra": {"use_ad_web_v2": true, "show_urls": ["https://ef-dongfeng.tanx.com/nnim?e=GmZjIC992oOgsWqVnuydz6Nwj84Yxx0NIq2lIhroRNxNI3KpE0TLIBqe_UFBokeRUAscoD_eyvAIkwt_bS0HduOtOnnqSEbs507zdlVLKIq5DIxv5EGl0uBq--JhPSpE&k=129&a1=__IP__&a2=__OS__&a3=__IDFA__&a4=__IMEI__&a5=__IMEI_MD5__&a6=__OAID__&a7=__MAC__&a8=__UA__&a9=__TS__"], "click_urls": ["https://ef-dongfeng.tanx.com/nncm?e=GmZjIC992oOgsWqVnuydz6Nwj84Yxx0NIq2lIhroRNxNI3KpE0TLIBqe_UFBokeRUAscoD_eyvAIkwt_bS0HduOtOnnqSEbs507zdlVLKIq5DIxv5EGl0uBq--JhPSpE&k=129&a1=__IP__&a2=__OS__&a3=__IDFA__&a4=__IMEI__&a5=__IMEI_MD5__&a6=__OAID__&a7=__MAC__&a8=__UA__&a9=__TS__"], "download_whitelist": [], "open_whitelist": ["tmall", "taobao", "ctrip", "openapp.jdmobile", "newsapp", "dianping", "vipshop", "kaola", "weixin", "alipays", "tbopen", "qunaraphone", "qunariphone", "eleme", "airbnb", "pddopen"], "report_time": 0, "sales_type": 41, "special_industry": false, "preload_landingpage": 0, "share_info": {}, "upzone_entrance_type": 0, "upzone_entrance_report_id": 0, "topview_pic_url": "", "topview_video_url": "", "click_area": 1}, "enable_pre_download": true, "enable_background_download": true}, {"id": 2244, "type": 1, "card_type": 14, "duration": 3, "begin_time": 1592323200, "end_time": 1592409599, "thumb": "https://i0.hdslb.com/bfs/sycp/creative_img/202006/a4b723914639a557ba3c2fff3558890d.jpg", "hash": "2ae7796fde6da9cf2030332a1cabcab4", "logo_url": "", "logo_hash": "", "skip": 1, "uri": "https://click.tanx.com/tfn?e=nSbqjYJMSwSpkqsHTUBO9yVzUgGGyYmmd2VikvfCygNETeaY8mdtlG0Bv7NeoFByBufPa%2b8o8tI7MPkz6vwMIpsS%2b8glEvWPhOViAsnHL07CJ%2fRR2dzkz0Ag%2bWElSh0WKJgzS%2bNWQ70%3d&u=https%3a%2f%2f618.tmall.com%2fmedia%3fdisableNav%3dYES%26bc_fl_src%3dtanx_df_147382634_0_17432_190808_59429_11872_10691_3%26resource_id%3d17432&k=140&ext=a%3d__IMEI__%26b%3d__IDFA__%26c%3d__MAC__%26d%3d__OAID__", "uri_title": "", "source": 929, "cm_mark": 1, "ad_cb": "<rm>", "resource_id": 926, "request_id": "<rm>", "client_ip": "47.92.120.142", "is_ad": true, "is_ad_loc": true, "schema": "tbopen://m.taobao.com/tbopen/index.html?action=ali.open.nav&bootImage=0&module=h5&source=alimama&visa=5d429034ad046701&appkey=24815762&bc_fl_src=tanx_df_147382634_0_17432_190808_59429_11872_10691_3&backURL=bilibili%3A%2F%2Fblank%3Fcm_mark%3Dxxx&packageName=AdxConstants.ANDROID_APP_PACKAGE_NAME&h5Url=https%3A%2F%2Fclick.tanx.com%2Ftfn%3Fe%3D3WxOfyxf%252f%252boN2WBaMN8K0QJR9P%252fmCwQWd2VikvfCygNETeaY8mdtlG0Bv7NeoFByBufPa%252b8o8tI7MPkz6vwMIpsS%252b8glEvWPhOViAsnHL07CJ%252fRR2dzkz0Ag%252bWElSh0WKJgzS%252bNWQ70%253d%26u%3Dhttps%253a%252f%252f618.tmall.com%252fmedia%253fdisableNav%253dYES%2526resource_id%253d17432%26k%3D140%26ext%3Da%253d__IMEI__%2526b%253d__IDFA__%2526c%253d__MAC__%2526d%253d__OAID__", "schema_title": "\u7acb\u5373\u67e5\u770b", "schema_package_name": "com.taobao.taobao", "schema_callup_white_list": ["tmall", "taobao", "ctrip", "openapp.jdmobile", "newsapp", "dianping", "vipshop", "kaola", "weixin", "alipays", "tbopen", "qunaraphone", "qunariphone", "eleme", "airbnb", "pddopen"], "universal_app": "tbopen://m.taobao.com/tbopen/index.html?action=ali.open.nav&bootImage=0&module=h5&source=alimama&visa=5d429034ad046701&appkey=24815762&bc_fl_src=tanx_df_147382634_0_17432_190808_59429_11872_10691_3&backURL=bilibili%3A%2F%2Fblank%3Fcm_mark%3Dxxx&packageName=AdxConstants.ANDROID_APP_PACKAGE_NAME&h5Url=https%3A%2F%2Fclick.tanx.com%2Ftfn%3Fe%3D3WxOfyxf%252f%252boN2WBaMN8K0QJR9P%252fmCwQWd2VikvfCygNETeaY8mdtlG0Bv7NeoFByBufPa%252b8o8tI7MPkz6vwMIpsS%252b8glEvWPhOViAsnHL07CJ%252fRR2dzkz0Ag%252bWElSh0WKJgzS%252bNWQ70%253d%26u%3Dhttps%253a%252f%252f618.tmall.com%252fmedia%253fdisableNav%253dYES%2526resource_id%253d17432%26k%3D140%26ext%3Da%253d__IMEI__%2526b%253d__IDFA__%2526c%253d__MAC__%2526d%253d__OAID__", "extra": {"use_ad_web_v2": true, "show_urls": ["https://ef-dongfeng.tanx.com/nnim?e=GmZjIC992oOgsWqVnuydz6Nwj84Yxx0NIq2lIhroRNxNI3KpE0TLIBqe_UFBokeRUAscoD_eyvAIkwt_bS0HduOtOnnqSEbs507zdlVLKIq5DIxv5EGl0uBq--JhPSpE&k=129&a1=__IP__&a2=__OS__&a3=__IDFA__&a4=__IMEI__&a5=__IMEI_MD5__&a6=__OAID__&a7=__MAC__&a8=__UA__&a9=__TS__"], "click_urls": ["https://ef-dongfeng.tanx.com/nncm?e=GmZjIC992oOgsWqVnuydz6Nwj84Yxx0NIq2lIhroRNxNI3KpE0TLIBqe_UFBokeRUAscoD_eyvAIkwt_bS0HduOtOnnqSEbs507zdlVLKIq5DIxv5EGl0uBq--JhPSpE&k=129&a1=__IP__&a2=__OS__&a3=__IDFA__&a4=__IMEI__&a5=__IMEI_MD5__&a6=__OAID__&a7=__MAC__&a8=__UA__&a9=__TS__"], "download_whitelist": [], "open_whitelist": ["tmall", "taobao", "ctrip", "openapp.jdmobile", "newsapp", "dianping", "vipshop", "kaola", "weixin", "alipays", "tbopen", "qunaraphone", "qunariphone", "eleme", "airbnb", "pddopen"], "report_time": 0, "sales_type": 41, "special_industry": false, "preload_landingpage": 0, "share_info": {}, "upzone_entrance_type": 0, "upzone_entrance_report_id": 0, "topview_pic_url": "", "topview_video_url": "", "click_area": 1}, "enable_pre_download": true, "enable_background_download": true}, {"id": 2245, "type": 1, "card_type": 14, "duration": 3, "begin_time": 1592323200, "end_time": 1592409599, "thumb": "https://i0.hdslb.com/bfs/sycp/creative_img/202006/c6eef4637e2841655e64c79b9c31be55.jpg", "hash": "f7b67903f0658b88cb96ba8a97ee6053", "logo_url": "", "logo_hash": "", "skip": 1, "uri": "https://click.tanx.com/tfn?e=nSbqjYJMSwSpkqsHTUBO9yVzUgGGyYmmd2VikvfCygNETeaY8mdtlG0Bv7NeoFByBufPa%2b8o8tI7MPkz6vwMIpsS%2b8glEvWPhOViAsnHL07CJ%2fRR2dzkz0Ag%2bWElSh0WKJgzS%2bNWQ70%3d&u=https%3a%2f%2f618.tmall.com%2fmedia%3fdisableNav%3dYES%26bc_fl_src%3dtanx_df_147382634_0_17432_190808_59429_11872_10691_3%26resource_id%3d17432&k=140&ext=a%3d__IMEI__%26b%3d__IDFA__%26c%3d__MAC__%26d%3d__OAID__", "uri_title": "", "source": 929, "cm_mark": 1, "ad_cb": "<rm>", "resource_id": 926, "request_id": "<rm>", "client_ip": "47.92.120.142", "is_ad": true, "is_ad_loc": true, "schema": "tbopen://m.taobao.com/tbopen/index.html?action=ali.open.nav&bootImage=0&module=h5&source=alimama&visa=5d429034ad046701&appkey=24815762&bc_fl_src=tanx_df_147382634_0_17432_190808_59429_11872_10691_3&backURL=bilibili%3A%2F%2Fblank%3Fcm_mark%3Dxxx&packageName=AdxConstants.ANDROID_APP_PACKAGE_NAME&h5Url=https%3A%2F%2Fclick.tanx.com%2Ftfn%3Fe%3D3WxOfyxf%252f%252boN2WBaMN8K0QJR9P%252fmCwQWd2VikvfCygNETeaY8mdtlG0Bv7NeoFByBufPa%252b8o8tI7MPkz6vwMIpsS%252b8glEvWPhOViAsnHL07CJ%252fRR2dzkz0Ag%252bWElSh0WKJgzS%252bNWQ70%253d%26u%3Dhttps%253a%252f%252f618.tmall.com%252fmedia%253fdisableNav%253dYES%2526resource_id%253d17432%26k%3D140%26ext%3Da%253d__IMEI__%2526b%253d__IDFA__%2526c%253d__MAC__%2526d%253d__OAID__", "schema_title": "\u7acb\u5373\u67e5\u770b", "schema_package_name": "com.taobao.taobao", "schema_callup_white_list": ["tmall", "taobao", "ctrip", "openapp.jdmobile", "newsapp", "dianping", "vipshop", "kaola", "weixin", "alipays", "tbopen", "qunaraphone", "qunariphone", "eleme", "airbnb", "pddopen"], "universal_app": "tbopen://m.taobao.com/tbopen/index.html?action=ali.open.nav&bootImage=0&module=h5&source=alimama&visa=5d429034ad046701&appkey=24815762&bc_fl_src=tanx_df_147382634_0_17432_190808_59429_11872_10691_3&backURL=bilibili%3A%2F%2Fblank%3Fcm_mark%3Dxxx&packageName=AdxConstants.ANDROID_APP_PACKAGE_NAME&h5Url=https%3A%2F%2Fclick.tanx.com%2Ftfn%3Fe%3D3WxOfyxf%252f%252boN2WBaMN8K0QJR9P%252fmCwQWd2VikvfCygNETeaY8mdtlG0Bv7NeoFByBufPa%252b8o8tI7MPkz6vwMIpsS%252b8glEvWPhOViAsnHL07CJ%252fRR2dzkz0Ag%252bWElSh0WKJgzS%252bNWQ70%253d%26u%3Dhttps%253a%252f%252f618.tmall.com%252fmedia%253fdisableNav%253dYES%2526resource_id%253d17432%26k%3D140%26ext%3Da%253d__IMEI__%2526b%253d__IDFA__%2526c%253d__MAC__%2526d%253d__OAID__", "extra": {"use_ad_web_v2": true, "show_urls": ["https://ef-dongfeng.tanx.com/nnim?e=GmZjIC992oOgsWqVnuydz6Nwj84Yxx0NIq2lIhroRNxNI3KpE0TLIBqe_UFBokeRUAscoD_eyvAIkwt_bS0HduOtOnnqSEbs507zdlVLKIq5DIxv5EGl0uBq--JhPSpE&k=129&a1=__IP__&a2=__OS__&a3=__IDFA__&a4=__IMEI__&a5=__IMEI_MD5__&a6=__OAID__&a7=__MAC__&a8=__UA__&a9=__TS__"], "click_urls": ["https://ef-dongfeng.tanx.com/nncm?e=GmZjIC992oOgsWqVnuydz6Nwj84Yxx0NIq2lIhroRNxNI3KpE0TLIBqe_UFBokeRUAscoD_eyvAIkwt_bS0HduOtOnnqSEbs507zdlVLKIq5DIxv5EGl0uBq--JhPSpE&k=129&a1=__IP__&a2=__OS__&a3=__IDFA__&a4=__IMEI__&a5=__IMEI_MD5__&a6=__OAID__&a7=__MAC__&a8=__UA__&a9=__TS__"], "download_whitelist": [], "open_whitelist": ["tmall", "taobao", "ctrip", "openapp.jdmobile", "newsapp", "dianping", "vipshop", "kaola", "weixin", "alipays", "tbopen", "qunaraphone", "qunariphone", "eleme", "airbnb", "pddopen"], "report_time": 0, "sales_type": 41, "special_industry": false, "preload_landingpage": 0, "share_info": {}, "upzone_entrance_type": 0, "upzone_entrance_report_id": 0, "topview_pic_url": "", "topview_video_url": "", "click_area": 1}, "enable_pre_download": true, "enable_background_download": true}, {"id": 2257, "type": 1, "card_type": 14, "duration": 3, "begin_time": 1592236800, "end_time": 1592323199, "thumb": "https://i0.hdslb.com/bfs/sycp/creative_img/202006/46ea624a72e353c645d6a1a356bc1787.jpg", "hash": "ad4775ecedd708d606a2e2ad0fb99afb", "logo_url": "", "logo_hash": "", "skip": 1, "uri": "https://click.tanx.com/tfn?e=tuJ%2f8Thm4yQ4wmnEZuzW1nS8PRVdI0%2bsd2VikvfCygNETeaY8mdtlG0Bv7NeoFByBufPa%2b8o8tIqDcAScqyaO2N7UhWaCzmgWBuZ9xbJobtoVe2nSaOBD0Ag%2bWElSh0WKJgzS%2bNWQ70%3d&u=https%3a%2f%2fwww.bilibili.com%2fblackboard%2factivity-tkKfIx7JJ.html%3fbc_fl_src%3dtanx_df_147382634_0_20822_202297_62211_12313_10912_3%26resource_id%3d20822&k=140&ext=a%3d__IMEI__%26b%3d__IDFA__%26c%3d__MAC__%26d%3d__OAID__", "uri_title": "", "source": 929, "cm_mark": 1, "ad_cb": "<rm>", "resource_id": 926, "request_id": "<rm>", "client_ip": "47.92.120.142", "is_ad": true, "is_ad_loc": true, "schema_callup_white_list": ["tmall", "taobao", "ctrip", "openapp.jdmobile", "newsapp", "dianping", "vipshop", "kaola", "weixin", "alipays", "tbopen", "qunaraphone", "qunariphone", "eleme", "airbnb", "pddopen"], "extra": {"use_ad_web_v2": true, "show_urls": ["https://ef-dongfeng.tanx.com/nnim?e=kakbJmHi5AigsWqVnuydz6Nwj84Yxx0NIq2lIhroRNxNI3KpE0TLIBqe_UFBokeRzIGEoIO3E8V7ISlKdqOmLOOtOnnqSEbs507zdlVLKIpAji1Y2-vd1Fy_vcDUl6ts&k=129&a1=__IP__&a2=__OS__&a3=__IDFA__&a4=__IMEI__&a5=__IMEI_MD5__&a6=__OAID__&a7=__MAC__&a8=__UA__&a9=__TS__"], "click_urls": ["https://ef-dongfeng.tanx.com/nncm?e=kakbJmHi5AigsWqVnuydz6Nwj84Yxx0NIq2lIhroRNxNI3KpE0TLIBqe_UFBokeRzIGEoIO3E8V7ISlKdqOmLOOtOnnqSEbs507zdlVLKIpAji1Y2-vd1Fy_vcDUl6ts&k=129&a1=__IP__&a2=__OS__&a3=__IDFA__&a4=__IMEI__&a5=__IMEI_MD5__&a6=__OAID__&a7=__MAC__&a8=__UA__&a9=__TS__"], "download_whitelist": [], "open_whitelist": ["tmall", "taobao", "ctrip", "openapp.jdmobile", "newsapp", "dianping", "vipshop", "kaola", "weixin", "alipays", "tbopen", "qunaraphone", "qunariphone", "eleme", "airbnb", "pddopen"], "report_time": 0, "sales_type": 41, "special_industry": false, "preload_landingpage": 0, "enable_share": true, "share_info": {"title": "\u8d85\u7ea7\u4e70\u5bb6\u79c0", "subtitle": "\u5168\u6c11\u5f00\u79c0\uff0c\u8d62\u5927\u5956", "image_url": "https://i0.hdslb.com/bfs/sycp/creative_img/202006/03a12b4ded7708e2208f689236bc0f4a.jpg"}, "upzone_entrance_type": 0, "upzone_entrance_report_id": 0, "topview_pic_url": "", "topview_video_url": "", "click_area": 1}, "enable_pre_download": true, "enable_background_download": true}, {"id": 2258, "type": 1, "card_type": 14, "duration": 3, "begin_time": 1592323200, "end_time": 1592409599, "thumb": "https://i0.hdslb.com/bfs/sycp/creative_img/202006/0511d5655467180d30501e56e4f4c90c.jpg", "hash": "ad4775ecedd708d606a2e2ad0fb99afb", "logo_url": "", "logo_hash": "", "skip": 1, "uri": "https://click.tanx.com/tfn?e=tuJ%2f8Thm4yQ4wmnEZuzW1nS8PRVdI0%2bsd2VikvfCygNETeaY8mdtlG0Bv7NeoFByBufPa%2b8o8tIqDcAScqyaO2N7UhWaCzmgWBuZ9xbJobtoVe2nSaOBD0Ag%2bWElSh0WKJgzS%2bNWQ70%3d&u=https%3a%2f%2fwww.bilibili.com%2fblackboard%2factivity-tkKfIx7JJ.html%3fbc_fl_src%3dtanx_df_147382634_0_20822_202297_62211_12313_10912_3%26resource_id%3d20822&k=140&ext=a%3d__IMEI__%26b%3d__IDFA__%26c%3d__MAC__%26d%3d__OAID__", "uri_title": "", "source": 929, "cm_mark": 1, "ad_cb": "<rm>", "resource_id": 926, "request_id": "<rm>", "client_ip": "47.92.120.142", "is_ad": true, "is_ad_loc": true, "schema_callup_white_list": ["tmall", "taobao", "ctrip", "openapp.jdmobile", "newsapp", "dianping", "vipshop", "kaola", "weixin", "alipays", "tbopen", "qunaraphone", "qunariphone", "eleme", "airbnb", "pddopen"], "extra": {"use_ad_web_v2": true, "show_urls": ["https://ef-dongfeng.tanx.com/nnim?e=kakbJmHi5AigsWqVnuydz6Nwj84Yxx0NIq2lIhroRNxNI3KpE0TLIBqe_UFBokeRzIGEoIO3E8V7ISlKdqOmLOOtOnnqSEbs507zdlVLKIpAji1Y2-vd1Fy_vcDUl6ts&k=129&a1=__IP__&a2=__OS__&a3=__IDFA__&a4=__IMEI__&a5=__IMEI_MD5__&a6=__OAID__&a7=__MAC__&a8=__UA__&a9=__TS__"], "click_urls": ["https://ef-dongfeng.tanx.com/nncm?e=kakbJmHi5AigsWqVnuydz6Nwj84Yxx0NIq2lIhroRNxNI3KpE0TLIBqe_UFBokeRzIGEoIO3E8V7ISlKdqOmLOOtOnnqSEbs507zdlVLKIpAji1Y2-vd1Fy_vcDUl6ts&k=129&a1=__IP__&a2=__OS__&a3=__IDFA__&a4=__IMEI__&a5=__IMEI_MD5__&a6=__OAID__&a7=__MAC__&a8=__UA__&a9=__TS__"], "download_whitelist": [], "open_whitelist": ["tmall", "taobao", "ctrip", "openapp.jdmobile", "newsapp", "dianping", "vipshop", "kaola", "weixin", "alipays", "tbopen", "qunaraphone", "qunariphone", "eleme", "airbnb", "pddopen"], "report_time": 0, "sales_type": 41, "special_industry": false, "preload_landingpage": 0, "enable_share": true, "share_info": {"title": "\u8d85\u7ea7\u4e70\u5bb6\u79c0", "subtitle": "\u5168\u6c11\u5f00\u79c0\uff0c\u8d62\u5927\u5956", "image_url": "https://i0.hdslb.com/bfs/sycp/creative_img/202006/4fc21829d1a6eb87cc99e576e454d52e.jpg"}, "upzone_entrance_type": 0, "upzone_entrance_report_id": 0, "topview_pic_url": "", "topview_video_url": "", "click_area": 1}, "enable_pre_download": true, "enable_background_download": true}, {"id": 2259, "type": 1, "card_type": 15, "duration": 3, "begin_time": 1592150400, "end_time": 1592236799, "thumb": "https://i0.hdslb.com/bfs/sycp/creative_img/202006/44e6ee57cf3b9cdff91527f326c19bd3.jpg", "hash": "70683b67f4c90c3f4a2ed8d117f67539", "logo_url": "", "logo_hash": "", "skip": 1, "uri": "https://www.bilibili.com/blackboard/activity-9jERjlU_j.html", "uri_title": "\u4e0b\u4e00\u4e2a\u641e\u7b11\u540d\u573a\u9762\uff0c\u7531\u4f60\u521b\u9020\uff01", "source": 929, "ad_cb": "<rm>", "resource_id": 926, "request_id": "<rm>", "client_ip": "47.92.120.142", "is_ad": true, "is_ad_loc": true, "extra": {"use_ad_web_v2": false, "show_urls": [], "click_urls": [], "download_whitelist": [], "open_whitelist": [], "report_time": 0, "sales_type": 41, "special_industry": false, "preload_landingpage": 0, "share_info": {}, "upzone_entrance_type": 0, "upzone_entrance_report_id": 0, "topview_pic_url": "", "topview_video_url": "", "click_area": 0}, "enable_pre_download": true, "enable_background_download": true}], "show": "<rm>"}}